LICENSE
README.rst
play_8.py
setup.cfg
setup.py
play_8.egg-info/PKG-INFO
play_8.egg-info/SOURCES.txt
play_8.egg-info/dependency_links.txt
play_8.egg-info/entry_points.txt
play_8.egg-info/requires.txt
play_8.egg-info/top_level.txt